paintcan-0.1.3.dist-info/METADATA
paintcan-0.1.3.dist-info/WHEEL
paintcan-0.1.3.dist-info/entry_points.txt
paintcan-0.1.3.dist-info/licenses/LICENSE
paintcan/__init__.py
paintcan/__main__.py
paintcan/color_scheme.py
paintcan/hsba_color.py
paintcan/py.typed
paintcan-0.1.3.dist-info/RECORD
