Metadata-Version: 2.1
Name: paintcan
Version: 0.1.3
Summary: A Pythonic library for creating beautiful, algorithmic color schemes.
Author-Email: "B.T. Franklin" <brandon.franklin@gmail.com>
License: MIT License
Classifier: Programming Language :: Python :: 3
Classifier: Programming Language :: Python :: 3 :: Only
Classifier: Programming Language :: Python :: 3.11
Classifier: Programming Language :: Python :: 3.12
Classifier: Programming Language :: Python :: 3.13
Classifier: Programming Language :: Python :: 3.14
Classifier: Typing :: Typed
Classifier: License :: OSI Approved :: MIT License
Classifier: Operating System :: OS Independent
Classifier: Intended Audience :: Developers
Classifier: Topic :: Software Development :: Libraries :: Python Modules
Classifier: Topic :: Multimedia :: Graphics
Project-URL: Homepage, https://github.com/btfranklin/paintcan
Project-URL: Issues, https://github.com/btfranklin/paintcan/issues
Project-URL: Repository, https://github.com/btfranklin/paintcan.git
Requires-Python: >=3.11
